availability/__init__.py
availability/profile.py
availability/sets.py
availability/util.py
availability_profile-0.0.1.dist-info/LICENSE
availability_profile-0.0.1.dist-info/METADATA
availability_profile-0.0.1.dist-info/WHEEL
availability_profile-0.0.1.dist-info/top_level.txt
availability_profile-0.0.1.dist-info/RECORD
