Metadata-Version: 2.1
Name: availability-profile
Version: 0.0.1
Summary: Data Structure for Tracking Computing Resource Availability
Author-email: Marcos Dias de Assuncao <assuncao@acm.org>
Maintainer-email: Marcos Dias de Assuncao <assuncao@acm.org>
License: MIT
Project-URL: Homepage, https://github.com/assuncaomarcos/resource-availability
Project-URL: Bug Reports, https://github.com/assuncaomarcos/resource-availability
Project-URL: Say Thanks!, https://saythanks.io/to/assuncaomarcos
Project-URL: Source, https://github.com/assuncaomarcos/resource-availability
Project-URL: documentation, http://resource-availability.readthedocs.io/
Keywords: data structure,resources,simulation,scheduling
Classifier: Development Status :: 3 - Alpha
Classifier: Intended Audience :: Developers
Classifier: Intended Audience :: Information Technology
Classifier: Topic :: Scientific/Engineering
Classifier: Topic :: Software Development :: Libraries
Classifier: License :: OSI Approved :: MIT License
Classifier: Programming Language :: Python :: 3
Classifier: Programming Language :: Python :: 3.8
Classifier: Programming Language :: Python :: 3.9
Classifier: Programming Language :: Python :: 3.10
Classifier: Programming Language :: Python :: 3.11
Classifier: Programming Language :: Python :: 3 :: Only
Classifier: Topic :: System :: Distributed Computing
Classifier: Topic :: System :: Monitoring
Classifier: Topic :: Utilities
Requires-Python: <4,>=3.7
License-File: LICENSE
Requires-Dist: sortedcontainers
Requires-Dist: Spans
Provides-Extra: dev
Requires-Dist: coverage (>=5.3) ; extra == 'dev'
Requires-Dist: black ; extra == 'dev'
Requires-Dist: build ; extra == 'dev'
Provides-Extra: docs
Requires-Dist: Sphinx ; extra == 'docs'
Requires-Dist: docutils ; extra == 'docs'
Requires-Dist: nbsphinx ; extra == 'docs'
Provides-Extra: test
Requires-Dist: coverage ; extra == 'test'
